{
  "kind": "singleType",
  "collectionName": "headers",
  "info": {
    "singularName": "header",
    "pluralName": "headers",
    "displayName": "Menu",
    "description": ""
  },
  "options": {
    "draftAndPublish": true
  },
  "pluginOptions": {},
  "attributes": {
    "targetItems": {
      "displayName": "NavigationItems",
      "type": "component",
      "repeatable": true,
      "component": "header.navigation-items",
      "required": true
    },
    "aboutItems": {
      "type": "component",
      "repeatable": true,
      "component": "header.navigation-items",
      "required": true
    },
    "login": {
      "type": "component",
      "repeatable": false,
      "component": "header.account-dropdown",
      "required": true
    },
    "signup": {
      "type": "component",
      "repeatable": false,
      "component": "header.account-dropdown",
      "required": true
    }
  }
}
